qspylib/__init__.py
qspylib/_version.py
qspylib/clublog.py
qspylib/eqsl.py
qspylib/logbook.py
qspylib/lotw.py
qspylib/qrz.py
qspylib/requirements.txt
qspylib/test_pytest.py
qspylib-1.0.0.dist-info/METADATA
qspylib-1.0.0.dist-info/WHEEL
qspylib-1.0.0.dist-info/licenses/LICENSE
qspylib-1.0.0.dist-info/RECORD
