Metadata-Version: 2.3
Name: qspylib
Version: 1.0.0
Summary: A set of API wrappers for different amateur radio websites, including LotW, QRZ, eQSL, and ClubLog
Project-URL: Homepage, https://github.com/JayToTheAy/QSPy
Project-URL: Documentation, https://qspylib.readthedocs.io/en/
Project-URL: Issues, https://github.com/JayToTheAy/QSPy/issues
Author-email: Jacob Humble <contact@jacobhumble.com>
Keywords: API,ClubLog,LOTW,QRZ,amateur radio,eQSL,ham radio
Classifier: Development Status :: 5 - Production/Stable
Classifier: Intended Audience :: Developers
Classifier: License :: OSI Approved :: Mozilla Public License 2.0 (MPL 2.0)
Classifier: Operating System :: OS Independent
Classifier: Programming Language :: Python :: 3
Classifier: Programming Language :: Python :: 3.9
Classifier: Programming Language :: Python :: 3.10
Classifier: Programming Language :: Python :: 3.11
Classifier: Programming Language :: Python :: 3.12
Classifier: Programming Language :: Python :: 3.13
Classifier: Topic :: Communications :: Ham Radio
Requires-Python: >=3.9
Requires-Dist: adif-io
Requires-Dist: requests
Requires-Dist: xmltodict
